{
	"pages": [ //pages数组中第一项表示应用启动页，参考：https://uniapp.dcloud.io/collocation/pages
		{
			"path": "pages/index/index",
			"style": {
				"navigationBarTitleText": "SpaceObj",
				"enablePullDownRefresh": false

			}
		}, {
			"path": "pages/project/project",
			"style": {
				"navigationBarTitleText": "SpaceObj",
				"enablePullDownRefresh": true
			}

		}, {
			"path": "pages/my/my",
			"style": {
				"navigationBarTitleText": "SpaceObj",
				"enablePullDownRefresh": false
			}

		}, {
			"path": "pages/release/release",
			"style": {
				"navigationBarTitleText": "SpaceObj",
				"enablePullDownRefresh": true

			}

		}, {
			"path": "pages/help/help",
			"style": {
				"navigationBarTitleText": "SpaceObj",
				"enablePullDownRefresh": true
			}

		}, {
			"path": "pages/projectDetail/projectDetail",
			"style": {
				"navigationBarTitleText": "SpaceObj",
				"enablePullDownRefresh": false
			}

		}, {
			"path": "pages/release/releaseProjectDetail/releaseProjectDetail",
			"style": {
				"navigationBarTitleText": "SpaceObj",
				"enablePullDownRefresh": false
			}

		}, {
			"path": "pages/help/helpProjectDetail/helpProjectDetail",
			"style": {
				"navigationBarTitleText": "SpaceObj",
				"enablePullDownRefresh": false
			}

		}, {
			"path": "pages/login/login",
			"style": {
				"navigationBarTitleText": "登录",
				"enablePullDownRefresh": false
			}

		}, {
			"path": "pages/my/editUser/editUser",
			"style": {
				"navigationBarTitleText": "编辑信息",
				"enablePullDownRefresh": false
			}

		}, {
			"path": "pages/my/auditProject/auditProject",
			"style": {
				"navigationBarTitleText": "SpaceObj",
				"enablePullDownRefresh": true
			}

		}, {
			"path": "pages/my/logManagement/logManagement",
			"style": {
				"navigationBarTitleText": "SpaceObj",
				"enablePullDownRefresh": false
			}

		}, {
			"path": "pages/my/userManageMent/userManageMent",
			"style": {
				"navigationBarTitleText": "SpaceObj",
				"enablePullDownRefresh": true
			}

		}, {
			"path": "pages/my/userVerified/userVerified",
			"style": {
				"navigationBarTitleText": "SpaceObj",
				"enablePullDownRefresh": false
			}

		}, {
			"path": "pages/my/photoManagement/photoManagement",
			"style": {
				"navigationBarTitleText": "SpaceObj",
				"enablePullDownRefresh": false
			}

		}, {
			"path": "pages/my/advertiseManagement/advertiseManagement",
			"style": {
				"navigationBarTitleText": "SpaceObj",
				"enablePullDownRefresh": false
			}

		}, {
			"path": "pages/my/userVerifiedMangeMent/userVerifiedMangeMent",
			"style": {
				"navigationBarTitleText": "SpaceObj",
				"enablePullDownRefresh": false
			}

		}, {
			"path": "pages/my/auditProject/auditProjectDetail/auditProjectDetail",
			"style": {
				"navigationBarTitleText": "SpaceObj",
				"enablePullDownRefresh": false
			}

		}, {
			"path": "pages/my/otherManagement/otherManagement",
			"style": {
				"navigationBarTitleText": "SpaceObj",
				"enablePullDownRefresh": false
			}

		}, {
			"path": "pages/my/logManagement/logDetail/logDetail",
			"style": {
				"navigationBarTitleText": "SpaceObj",
				"enablePullDownRefresh": false
			}

		}, {
			"path": "pages/addEmailPhoneNumber/addEmailPhoneNumber",
			"style": {
				"navigationBarTitleText": "",
				"enablePullDownRefresh": false
			}

		}, {
			"path": "pages/index/index2/index2",
			"style": {
				"navigationBarTitleText": "",
				"enablePullDownRefresh": false
			}

		}
	],
	"globalStyle": {
		"navigationBarTextStyle": "black",
		"navigationBarTitleText": "uni-app",
		"navigationBarBackgroundColor": "#F8F8F8",
		"backgroundColor": "#F8F8F8"
	},
	"tabBar": {
		"color": "#cdcdcd",
		"selectedColor": "#49A8E7",
		"borderStyle": "black",
		"backgroundColor": "#ffffff",
		"height": "50px",
		"fontSize": "10px",
		"iconWidth": "24px",
		"spacing": "3px",
		"list": [{
				"pagePath": "pages/project/project",
				"iconPath": "static/project.png",
				"selectedIconPath": "static/selectProject.png",
				"text": "首页"
			},
			// {
			// 	"pagePath": "pages/help/help",
			// 	"iconPath": "static/help.png",
			// 	"selectedIconPath": "static/selectHelp.png",
			// 	"text": "好友助力"
			// },
			// {
			// 	"pagePath": "pages/release/release",
			// 	"iconPath": "static/release.png",
			// 	"selectedIconPath": "static/selectRelease.png",
			// 	"text": "我的发布"
			// },

			{
				"pagePath": "pages/my/my",
				"iconPath": "static/my.png",
				"selectedIconPath": "static/selectMy.png",
				"text": "我的"
			}
		]
	}
}
